.gitignore
CHANGELOG.md
LICENSE
README_ES.md
TODO.md
boli_orbital_api/__init__.py
boli_orbital_api/logger.py
boli_orbital_api/rpc.py
requirements.txt
requirements_freezed.txt
boli_orbital_api-0.9b17.dist-info/LICENSE
boli_orbital_api-0.9b17.dist-info/METADATA
boli_orbital_api-0.9b17.dist-info/WHEEL
boli_orbital_api-0.9b17.dist-info/RECORD
