Metadata-Version: 2.1
Name: boli-orbital-api
Version: 0.9b17
Summary: Orbital API RPC for Bolivarcoin/Bolicoin blockchain
Home-page: https://orbital.center
License: MIT
Keywords: bolicoin,bolivarcoin,criptocurrency,blockchain,api
Author: Asdrubal Velasquez Lagrave
Author-email: hello@orbital.center
Maintainer: Asdrubal Velasquez Lagrave
Maintainer-email: hello@orbital.center
Requires-Python: >=3.10,<4.0
Classifier: Development Status :: 4 - Beta
Classifier: Intended Audience :: Developers
Classifier: License :: OSI Approved :: MIT License
Classifier: Operating System :: OS Independent
Classifier: Programming Language :: Python
Classifier: Programming Language :: Python :: 3
Classifier: Programming Language :: Python :: 3.10
Classifier: Programming Language :: Python :: 3.11
Classifier: Topic :: Software Development
Requires-Dist: orjson (>=3.8.14,<4.0.0)
Requires-Dist: requests (>=2.31.0,<3.0.0)
Project-URL: Repository, https://github.com/Visionario/BoliOrbitalAPI
